{
  "name": "Smelter Presentation GS",
  "shaders": [
    {
      "shaderName": "Ultra Key",
      "shaderId": "ultra-key",
      "enabled": true,
      "params": [
        {
          "paramName": "key_color",
          "paramValue": 7312773
        },
        {
          "paramName": "hue_width",
          "paramValue": 0.12
        },
        {
          "paramName": "hue_softness",
          "paramValue": 0.06
        },
        {
          "paramName": "sat_threshold",
          "paramValue": 0.15
        },
        {
          "paramName": "sat_softness",
          "paramValue": 0.1
        },
        {
          "paramName": "luma_low",
          "paramValue": 0.05
        },
        {
          "paramName": "luma_high",
          "paramValue": 0.95
        },
        {
          "paramName": "luma_softness",
          "paramValue": 0.05
        },
        {
          "paramName": "erode",
          "paramValue": 0
        },
        {
          "paramName": "clip_low",
          "paramValue": 0
        },
        {
          "paramName": "clip_high",
          "paramValue": 1
        },
        {
          "paramName": "matte_gamma",
          "paramValue": 1
        },
        {
          "paramName": "despill",
          "paramValue": 0.5
        },
        {
          "paramName": "despill_balance",
          "paramValue": 0
        },
        {
          "paramName": "fg_brightness",
          "paramValue": 0
        },
        {
          "paramName": "fg_saturation",
          "paramValue": 1
        }
      ]
    },
    {
      "shaderName": "Comic Book",
      "shaderId": "comic-book",
      "enabled": true,
      "params": [
        {
          "paramName": "ink_color",
          "paramValue": 0
        },
        {
          "paramName": "edge_strength",
          "paramValue": 0
        },
        {
          "paramName": "edge_thickness",
          "paramValue": 1.44
        },
        {
          "paramName": "color_levels",
          "paramValue": 7.88
        },
        {
          "paramName": "saturation_boost",
          "paramValue": 0.57
        },
        {
          "paramName": "halftone_size",
          "paramValue": 4
        },
        {
          "paramName": "halftone_strength",
          "paramValue": 0.46
        },
        {
          "paramName": "ink_smoothness",
          "paramValue": 0.68
        },
        {
          "paramName": "paper_warmth",
          "paramValue": 0.15
        },
        {
          "paramName": "brightness",
          "paramValue": 1.15
        },
        {
          "paramName": "speed_lines",
          "paramValue": 0.44
        },
        {
          "paramName": "speed_line_density",
          "paramValue": 30
        }
      ]
    },
    {
      "shaderName": "HSL Adjust",
      "shaderId": "hsl-adjust",
      "enabled": true,
      "params": [
        {
          "paramName": "hue_shift",
          "paramValue": -0.54
        },
        {
          "paramName": "saturation",
          "paramValue": -0.19
        },
        {
          "paramName": "lightness",
          "paramValue": 0
        },
        {
          "paramName": "colorize_enable",
          "paramValue": 0.2
        },
        {
          "paramName": "colorize_hue",
          "paramValue": 0.86
        },
        {
          "paramName": "colorize_saturation",
          "paramValue": 0.37
        },
        {
          "paramName": "mix_amount",
          "paramValue": 1
        }
      ]
    }
  ],
  "savedAt": "2026-03-31T00:58:31.718Z"
}